latitudesh_python_sdk/__init__.py
latitudesh_python_sdk/_hooks/__init__.py
latitudesh_python_sdk/_hooks/registration.py
latitudesh_python_sdk/_hooks/sdkhooks.py
latitudesh_python_sdk/_hooks/types.py
latitudesh_python_sdk/_version.py
latitudesh_python_sdk/apikeys.py
latitudesh_python_sdk/basesdk.py
latitudesh_python_sdk/billing.py
latitudesh_python_sdk/events_sdk.py
latitudesh_python_sdk/firewalls_sdk.py
latitudesh_python_sdk/httpclient.py
latitudesh_python_sdk/ipaddresses_sdk.py
latitudesh_python_sdk/models/__init__.py
latitudesh_python_sdk/models/api_key.py
latitudesh_python_sdk/models/apierror.py
latitudesh_python_sdk/models/assign_server_virtual_networkop.py
latitudesh_python_sdk/models/bandwidth_packages.py
latitudesh_python_sdk/models/bandwidth_plan_data.py
latitudesh_python_sdk/models/bandwidth_plans.py
latitudesh_python_sdk/models/billing_usage.py
latitudesh_python_sdk/models/container_plan_data.py
latitudesh_python_sdk/models/create_api_key.py
latitudesh_python_sdk/models/create_firewall_assignmentop.py
latitudesh_python_sdk/models/create_firewallop.py
latitudesh_python_sdk/models/create_ipmi_sessionop.py
latitudesh_python_sdk/models/create_projectop.py
latitudesh_python_sdk/models/create_server_actionop.py
latitudesh_python_sdk/models/create_server_out_of_bandop.py
latitudesh_python_sdk/models/create_server_reinstallop.py
latitudesh_python_sdk/models/create_serverop.py
latitudesh_python_sdk/models/create_tagop.py
latitudesh_python_sdk/models/create_virtual_machine_actionop.py
latitudesh_python_sdk/models/create_virtual_networkop.py
latitudesh_python_sdk/models/custom_tag.py
latitudesh_python_sdk/models/custom_tag_data.py
latitudesh_python_sdk/models/custom_tags.py
latitudesh_python_sdk/models/delete_api_keyop.py
latitudesh_python_sdk/models/delete_firewall_assignmentop.py
latitudesh_python_sdk/models/delete_firewallop.py
latitudesh_python_sdk/models/delete_project_ssh_keyop.py
latitudesh_python_sdk/models/delete_project_user_dataop.py
latitudesh_python_sdk-2.3.1.dist-info/METADATA
latitudesh_python_sdk-2.3.1.dist-info/WHEEL
latitudesh_python_sdk-2.3.1.dist-info/licenses/LICENSE
latitudesh_python_sdk-2.3.1.dist-info/RECORD
